gaiapy/__init__.py
gaiapy/api.py
gaiapy/core/__init__.py
gaiapy/core/ancestry.py
gaiapy/core/discrete.py
gaiapy/core/linear.py
gaiapy/core/quadratic.py
gaiapy/core/sankoff.py
gaiapy/utils/__init__.py
gaiapy/utils/metadata.py
gaiapy/utils/tree_utils.py
gaiapy/utils/validation.py
geoancestry-0.1.2.dist-info/METADATA
geoancestry-0.1.2.dist-info/WHEEL
geoancestry-0.1.2.dist-info/top_level.txt
geoancestry-0.1.2.dist-info/RECORD
