Metadata-Version: 2.4
Name: geoancestry
Version: 0.1.2
Summary: Geographic Ancestry Inference Algorithm - Python implementation (continuous space parsimony methods)
Author: Adapted from Michael C. Grundler's GAIA R package
License-Expression: MIT
Project-URL: Homepage, https://github.com/chris-a-talbot/gaiapy
Project-URL: Repository, https://github.com/chris-a-talbot/gaiapy
Project-URL: Issues, https://github.com/chris-a-talbot/gaiapy/issues
Classifier: Development Status :: 3 - Alpha
Classifier: Intended Audience :: Science/Research
Classifier: Operating System :: OS Independent
Classifier: Programming Language :: Python :: 3
Classifier: Programming Language :: Python :: 3.8
Classifier: Programming Language :: Python :: 3.9
Classifier: Programming Language :: Python :: 3.10
Classifier: Programming Language :: Python :: 3.11
Classifier: Topic :: Scientific/Engineering :: Bio-Informatics
Requires-Python: >=3.8
Requires-Dist: numpy>=1.20.0
Requires-Dist: tskit>=0.5.0
Requires-Dist: scipy>=1.7.0
Provides-Extra: dev
Requires-Dist: pytest; extra == "dev"
Requires-Dist: pytest-cov; extra == "dev"
Requires-Dist: black; extra == "dev"
Requires-Dist: flake8; extra == "dev"
Provides-Extra: docs
Requires-Dist: sphinx; extra == "docs"
Requires-Dist: sphinx-rtd-theme; extra == "docs"
